a_pandas_ex_string_to_dtypes/LICENSE
a_pandas_ex_string_to_dtypes/README.MD
a_pandas_ex_string_to_dtypes/__init__.py
a_pandas_ex_string_to_dtypes/requirements.txt
a_pandas_ex_string_to_dtypes/thirdparty.json
a_pandas_ex_string_to_dtypes-0.1.dist-info/LICENSE.rst
a_pandas_ex_string_to_dtypes-0.1.dist-info/METADATA
a_pandas_ex_string_to_dtypes-0.1.dist-info/WHEEL
a_pandas_ex_string_to_dtypes-0.1.dist-info/top_level.txt
a_pandas_ex_string_to_dtypes-0.1.dist-info/RECORD
