Metadata-Version: 2.1
Name: a_pandas_ex_string_to_dtypes
Version: 0.1
Summary: Convert a Pandas DataFrame/Series with dtype str/string/object to the best available dtypes
Home-page: https://github.com/hansalemaos/a_pandas_ex_string_to_dtypes
Author: Johannes Fischer
Author-email: <aulasparticularesdealemaosp@gmail.com>
License: MIT
Keywords: pandas,dtypes,converter
Classifier: Development Status :: 4 - Beta
Classifier: Programming Language :: Python :: 3 :: Only
Classifier: Programming Language :: Python :: 3.9
Classifier: Topic :: Scientific/Engineering :: Visualization
Classifier: Topic :: Software Development :: Libraries :: Python Modules
Classifier: Topic :: Text Editors :: Text Processing
Classifier: Topic :: Text Processing :: General
Classifier: Topic :: Text Processing :: Indexing
Classifier: Topic :: Text Processing :: Filters
Classifier: Topic :: Utilities
License-File: LICENSE.rst
